README.txt
setup.py
datecharts/__init__.py
datecharts/graphplotting.py
datecharts.egg-info/PKG-INFO
datecharts.egg-info/SOURCES.txt
datecharts.egg-info/dependency_links.txt
datecharts.egg-info/requires.txt
datecharts.egg-info/top_level.txt