Metadata-Version: 1.1
Name: datecharts
Version: 1.0.3
Summary: Simple utility to graph time series data
Home-page: UNKNOWN
Author: Petr Pavlu
Author-email: ppavlu@cisco.com
License: MIT
Keywords: time series data graph chart plot
Platform: UNKNOWN
Classifier: Development Status :: 3 - Alpha
Classifier: License :: OSI Approved :: MIT License
Classifier: Programming Language :: Python :: 3.4
